{"version": "1.1", "sections": [{"title": "Containerized installation", "visible": true, "weight": 1, "urlFragment": "index", "anchor": null, "singlePageAnchor": null}, {"title": "Providing feedback on Red Hat documentation", "visible": true, "weight": 2, "urlFragment": "providing-feedback", "anchor": null, "singlePageAnchor": "providing-feedback"}, {"title": "1. Managing Ansible Automation Platform licensing, updates and support", "visible": true, "weight": 3, "urlFragment": "assembly-gateway-licensing", "anchor": null, "singlePageAnchor": "assembly-gateway-licensing", "sections": [{"title": "1.1. Trial and evaluation", "visible": true, "weight": 1, "urlFragment": "assembly-gateway-licensing", "anchor": "ref-controller-trial-evaluation", "singlePageAnchor": "ref-controller-trial-evaluation"}, {"title": "1.2. Component licenses", "visible": true, "weight": 2, "urlFragment": "assembly-gateway-licensing", "anchor": "ref-controller-licenses", "singlePageAnchor": "ref-controller-licenses"}, {"title": "1.3. Node counting in licenses", "visible": true, "weight": 3, "urlFragment": "assembly-gateway-licensing", "anchor": "ref-controller-node-counting", "singlePageAnchor": "ref-controller-node-counting"}, {"title": "1.4. Subscription Types", "visible": true, "weight": 4, "urlFragment": "assembly-gateway-licensing", "anchor": "ref-controller-subscription-types", "singlePageAnchor": "ref-controller-subscription-types"}, {"title": "1.5. Attaching your Red Hat Ansible Automation Platform subscription", "visible": true, "weight": 5, "urlFragment": "assembly-gateway-licensing", "anchor": "proc-attaching-subscriptions", "singlePageAnchor": "proc-attaching-subscriptions"}, {"title": "1.6. Obtaining a manifest file", "visible": true, "weight": 6, "urlFragment": "assembly-gateway-licensing", "anchor": "assembly-aap-obtain-manifest-files", "singlePageAnchor": "assembly-aap-obtain-manifest-files", "sections": [{"title": "1.6.1. Create a subscription allocation", "visible": true, "weight": 1, "urlFragment": "assembly-gateway-licensing", "anchor": "proc-create-subscription-allocation_obtain-manifest", "singlePageAnchor": "proc-create-subscription-allocation_obtain-manifest"}, {"title": "1.6.2. Adding subscriptions to a subscription allocation", "visible": true, "weight": 2, "urlFragment": "assembly-gateway-licensing", "anchor": "proc-add-merge-subscriptions", "singlePageAnchor": "proc-add-merge-subscriptions"}, {"title": "1.6.3. Downloading a manifest file", "visible": true, "weight": 3, "urlFragment": "assembly-gateway-licensing", "anchor": "proc-aap-generate-manifest-file", "singlePageAnchor": "proc-aap-generate-manifest-file"}]}, {"title": "1.7. Activating Red Hat Ansible Automation Platform", "visible": true, "weight": 7, "urlFragment": "assembly-gateway-licensing", "anchor": "assembly-aap-activate", "singlePageAnchor": "assembly-aap-activate", "sections": [{"title": "1.7.1. Activate with credentials", "visible": true, "weight": 1, "urlFragment": "assembly-gateway-licensing", "anchor": "proc-aap-activate-with-credentials", "singlePageAnchor": "proc-aap-activate-with-credentials"}, {"title": "1.7.2. Activate with a manifest file", "visible": true, "weight": 2, "urlFragment": "assembly-gateway-licensing", "anchor": "proc-aap-activate-with-manifest", "singlePageAnchor": "proc-aap-activate-with-manifest"}]}]}, {"title": "2. Ansible Automation Platform containerized installation", "visible": true, "weight": 4, "urlFragment": "aap-containerized-installation", "anchor": null, "singlePageAnchor": "aap-containerized-installation", "sections": [{"title": "2.1. Tested deployment topologies", "visible": true, "weight": 1, "urlFragment": "aap-containerized-installation", "anchor": "tested_deployment_topologies", "singlePageAnchor": "tested_deployment_topologies"}, {"title": "2.2. System requirements", "visible": true, "weight": 2, "urlFragment": "aap-containerized-installation", "anchor": "system-requirements", "singlePageAnchor": "system-requirements", "sections": [{"title": "2.2.1. Ansible Automation Platform system requirements", "visible": true, "weight": 1, "urlFragment": "aap-containerized-installation", "anchor": "ansible_automation_platform_system_requirements", "singlePageAnchor": "ansible_automation_platform_system_requirements"}, {"title": "2.2.2. Database requirements", "visible": true, "weight": 2, "urlFragment": "aap-containerized-installation", "anchor": "database_requirements", "singlePageAnchor": "database_requirements"}]}, {"title": "2.3. Preparing the Red Hat Enterprise Linux host for containerized installation", "visible": true, "weight": 3, "urlFragment": "aap-containerized-installation", "anchor": "preparing-the-rhel-host-for-containerized-installation", "singlePageAnchor": "preparing-the-rhel-host-for-containerized-installation"}, {"title": "2.4. Preparing the managed nodes for containerized installation", "visible": true, "weight": 4, "urlFragment": "aap-containerized-installation", "anchor": "preparing-the-managed-nodes-for-containerized-installation", "singlePageAnchor": "preparing-the-managed-nodes-for-containerized-installation"}, {"title": "2.5. Downloading Ansible Automation Platform", "visible": true, "weight": 5, "urlFragment": "aap-containerized-installation", "anchor": "downloading-ansible-automation-platform", "singlePageAnchor": "downloading-ansible-automation-platform"}, {"title": "2.6. Configuring the inventory file", "visible": true, "weight": 6, "urlFragment": "aap-containerized-installation", "anchor": "configuring-inventory-file", "singlePageAnchor": "configuring-inventory-file", "sections": [{"title": "2.6.1. Inventory file for online installation for containerized growth topology (all-in-one)", "visible": true, "weight": 1, "urlFragment": "aap-containerized-installation", "anchor": "inventory_file_for_online_installation_for_containerized_growth_topology_all_in_one", "singlePageAnchor": "inventory_file_for_online_installation_for_containerized_growth_topology_all_in_one"}, {"title": "2.6.2. Inventory file for online installation for containerized enterprise topology", "visible": true, "weight": 2, "urlFragment": "aap-containerized-installation", "anchor": "inventory_file_for_online_installation_for_containerized_enterprise_topology", "singlePageAnchor": "inventory_file_for_online_installation_for_containerized_enterprise_topology"}, {"title": "2.6.3. Performing an offline or bundled installation", "visible": true, "weight": 3, "urlFragment": "aap-containerized-installation", "anchor": "performing_an_offline_or_bundled_installation", "singlePageAnchor": "performing_an_offline_or_bundled_installation"}, {"title": "2.6.4. Setting registry_username and registry_password", "visible": true, "weight": 4, "urlFragment": "aap-containerized-installation", "anchor": "proc-set-registry-username-password", "singlePageAnchor": "proc-set-registry-username-password"}]}, {"title": "2.7. Advanced configuration options", "visible": true, "weight": 7, "urlFragment": "aap-containerized-installation", "anchor": "advanced_configuration_options", "singlePageAnchor": "advanced_configuration_options", "sections": [{"title": "2.7.1. Adding a safe plugin variable to Event-Driven Ansible controller", "visible": true, "weight": 1, "urlFragment": "aap-containerized-installation", "anchor": "proc-add-eda-safe-plugin-var", "singlePageAnchor": "proc-add-eda-safe-plugin-var"}, {"title": "2.7.2. Adding execution nodes", "visible": true, "weight": 2, "urlFragment": "aap-containerized-installation", "anchor": "adding-execution-nodes_aap-containerized-installation", "singlePageAnchor": "adding-execution-nodes_aap-containerized-installation"}, {"title": "2.7.3. Configuring storage for automation hub", "visible": true, "weight": 3, "urlFragment": "aap-containerized-installation", "anchor": "configuring-storage-for-automation-hub", "singlePageAnchor": "configuring-storage-for-automation-hub", "sections": [{"title": "2.7.3.1. Configuring Amazon S3 storage for automation hub", "visible": false, "weight": 1, "urlFragment": "aap-containerized-installation", "anchor": "configure-hub-s3-storage", "singlePageAnchor": "configure-hub-s3-storage"}, {"title": "2.7.3.2. Configuring Azure Blob Storage for automation hub", "visible": false, "weight": 2, "urlFragment": "aap-containerized-installation", "anchor": "configure-hub-azure-storage", "singlePageAnchor": "configure-hub-azure-storage"}, {"title": "2.7.3.3. Configuring Network File System (NFS) storage for automation hub", "visible": false, "weight": 3, "urlFragment": "aap-containerized-installation", "anchor": "configure-hub-nfs-storage", "singlePageAnchor": "configure-hub-nfs-storage"}]}, {"title": "2.7.4. Configuring a HAProxy load balancer", "visible": true, "weight": 4, "urlFragment": "aap-containerized-installation", "anchor": "configuring-haproxy-load-balancer", "singlePageAnchor": "configuring-haproxy-load-balancer"}, {"title": "2.7.5. Enabling automation content collection and container signing", "visible": true, "weight": 5, "urlFragment": "aap-containerized-installation", "anchor": "enabling-automation-hub-collection-and-container-signing_aap-containerized-installation", "singlePageAnchor": "enabling-automation-hub-collection-and-container-signing_aap-containerized-installation"}, {"title": "2.7.6. Setting up a customer provided (external) database", "visible": true, "weight": 6, "urlFragment": "aap-containerized-installation", "anchor": "setting-up-a-customer-provided-external-database", "singlePageAnchor": "setting-up-a-customer-provided-external-database", "sections": [{"title": "2.7.6.1. Setting up an external database with PostgreSQL admin credentials", "visible": false, "weight": 1, "urlFragment": "aap-containerized-installation", "anchor": "setup-ext-db-with-admin-creds", "singlePageAnchor": "setup-ext-db-with-admin-creds"}, {"title": "2.7.6.2. Setting up an external database without PostgreSQL admin credentials", "visible": false, "weight": 2, "urlFragment": "aap-containerized-installation", "anchor": "setup-ext-db-without-admin-creds", "singlePageAnchor": "setup-ext-db-without-admin-creds"}, {"title": "2.7.6.3. Enabling the hstore extension for the automation hub PostgreSQL database", "visible": false, "weight": 3, "urlFragment": "aap-containerized-installation", "anchor": "proc-enable-hstore-extension", "singlePageAnchor": "proc-enable-hstore-extension"}, {"title": "2.7.6.4. Optional: configuring mutual TLS (mTLS) authentication for an external database", "visible": false, "weight": 4, "urlFragment": "aap-containerized-installation", "anchor": "configure-ext-db-mtls", "singlePageAnchor": "configure-ext-db-mtls"}]}, {"title": "2.7.7. Using custom TLS certificates", "visible": true, "weight": 7, "urlFragment": "aap-containerized-installation", "anchor": "using-custom-tls-certificates", "singlePageAnchor": "using-custom-tls-certificates", "sections": [{"title": "2.7.7.1. Ansible Automation Platform generated certificates", "visible": false, "weight": 1, "urlFragment": "aap-containerized-installation", "anchor": "installer-generated-certificates", "singlePageAnchor": "installer-generated-certificates"}, {"title": "2.7.7.2. User-provided certificates", "visible": false, "weight": 2, "urlFragment": "aap-containerized-installation", "anchor": "user_provided_certificates", "singlePageAnchor": "user_provided_certificates", "sections": [{"title": "2.7.7.2.1. Using a custom CA to generate all TLS certificates", "visible": false, "weight": 1, "urlFragment": "aap-containerized-installation", "anchor": "use-custom-ca-certs", "singlePageAnchor": "use-custom-ca-certs"}, {"title": "2.7.7.2.2. Providing custom TLS certificates for each service", "visible": false, "weight": 2, "urlFragment": "aap-containerized-installation", "anchor": "proc-provide-custom-tls-certs-per-service", "singlePageAnchor": "proc-provide-custom-tls-certs-per-service"}, {"title": "2.7.7.2.3. Considerations for certificates provided per service", "visible": false, "weight": 3, "urlFragment": "aap-containerized-installation", "anchor": "certs-per-service-considerations", "singlePageAnchor": "certs-per-service-considerations"}, {"title": "2.7.7.2.4. Providing a custom CA certificate", "visible": false, "weight": 4, "urlFragment": "aap-containerized-installation", "anchor": "providing-a-custom-ca-certificate", "singlePageAnchor": "providing-a-custom-ca-certificate"}]}, {"title": "2.7.7.3. Receptor certificate considerations", "visible": false, "weight": 3, "urlFragment": "aap-containerized-installation", "anchor": "receptor-certificate-considerations", "singlePageAnchor": "receptor-certificate-considerations"}]}, {"title": "2.7.8. Using custom Receptor signing keys", "visible": true, "weight": 8, "urlFragment": "aap-containerized-installation", "anchor": "using-custom-receptor-signing-keys_aap-containerized-installation", "singlePageAnchor": "using-custom-receptor-signing-keys_aap-containerized-installation"}]}, {"title": "2.8. Installing containerized Ansible Automation Platform", "visible": true, "weight": 8, "urlFragment": "aap-containerized-installation", "anchor": "installing-containerized-aap", "singlePageAnchor": "installing-containerized-aap"}, {"title": "2.9. Updating containerized Ansible Automation Platform", "visible": true, "weight": 9, "urlFragment": "aap-containerized-installation", "anchor": "updating-containerized-ansible-automation-platform", "singlePageAnchor": "updating-containerized-ansible-automation-platform"}, {"title": "2.10. Backing up containerized Ansible Automation Platform", "visible": true, "weight": 10, "urlFragment": "aap-containerized-installation", "anchor": "backing-up-containerized-ansible-automation-platform", "singlePageAnchor": "backing-up-containerized-ansible-automation-platform"}, {"title": "2.11. Restoring containerized Ansible Automation Platform", "visible": true, "weight": 11, "urlFragment": "aap-containerized-installation", "anchor": "proc-restore-aap-container", "singlePageAnchor": "proc-restore-aap-container"}, {"title": "2.12. Uninstalling containerized Ansible Automation Platform", "visible": true, "weight": 12, "urlFragment": "aap-containerized-installation", "anchor": "uninstalling-containerized-aap", "singlePageAnchor": "uninstalling-containerized-aap"}, {"title": "2.13. Reinstalling containerized Ansible Automation Platform", "visible": true, "weight": 13, "urlFragment": "aap-containerized-installation", "anchor": "reinstalling-containerized-aap", "singlePageAnchor": "reinstalling-containerized-aap"}]}, {"title": "3. Horizontal Scaling in Red Hat Ansible Automation Platform", "visible": true, "weight": 5, "urlFragment": "assembly-horizontal-scaling", "anchor": null, "singlePageAnchor": "assembly-horizontal-scaling", "sections": [{"title": "3.1. Horizontal scaling in Event-Driven Ansible controller", "visible": true, "weight": 1, "urlFragment": "assembly-horizontal-scaling", "anchor": "con-hs-eda-controller", "singlePageAnchor": "con-hs-eda-controller", "sections": [{"title": "3.1.1. Sizing and scaling guidelines", "visible": true, "weight": 1, "urlFragment": "assembly-horizontal-scaling", "anchor": "con-hs-eda-sizing-scaling", "singlePageAnchor": "con-hs-eda-sizing-scaling"}, {"title": "3.1.2. Setting up horizontal scaling for Event-Driven Ansible controller", "visible": true, "weight": 2, "urlFragment": "assembly-horizontal-scaling", "anchor": "proc-hs-eda-setup", "singlePageAnchor": "proc-hs-eda-setup"}]}]}, {"title": "A. Troubleshooting containerized Ansible Automation Platform", "visible": true, "weight": 6, "urlFragment": "troubleshooting-containerized-ansible-automation-platform", "anchor": null, "singlePageAnchor": "troubleshooting-containerized-ansible-automation-platform", "sections": [{"title": "A.1. Gathering Ansible Automation Platform logs", "visible": true, "weight": 1, "urlFragment": "troubleshooting-containerized-ansible-automation-platform", "anchor": "gathering-ansible-automation-platform-logs_troubleshooting-containerized-aap", "singlePageAnchor": "gathering-ansible-automation-platform-logs_troubleshooting-containerized-aap"}, {"title": "A.2. Diagnosing the problem", "visible": true, "weight": 2, "urlFragment": "troubleshooting-containerized-ansible-automation-platform", "anchor": "diagnosing-the-problem_troubleshooting-containerized-aap", "singlePageAnchor": "diagnosing-the-problem_troubleshooting-containerized-aap"}, {"title": "A.3. Troubleshooting containerized Ansible Automation Platform installation", "visible": true, "weight": 3, "urlFragment": "troubleshooting-containerized-ansible-automation-platform", "anchor": "troubleshooting-containerized-ansible-automation-platform-installation_troubleshooting-containerized-aap", "singlePageAnchor": "troubleshooting-containerized-ansible-automation-platform-installation_troubleshooting-containerized-aap"}, {"title": "A.4. Troubleshooting containerized Ansible Automation Platform configuration", "visible": true, "weight": 4, "urlFragment": "troubleshooting-containerized-ansible-automation-platform", "anchor": "troubleshooting-containerized-ansible-automation-platform-configuration_troubleshooting-containerized-aap", "singlePageAnchor": "troubleshooting-containerized-ansible-automation-platform-configuration_troubleshooting-containerized-aap"}, {"title": "A.5. Containerized Ansible Automation Platform reference", "visible": true, "weight": 5, "urlFragment": "troubleshooting-containerized-ansible-automation-platform", "anchor": "containerized-ansible-automation-platform-reference_troubleshooting-containerized-aap", "singlePageAnchor": "containerized-ansible-automation-platform-reference_troubleshooting-containerized-aap"}]}, {"title": "B. Inventory file variables", "visible": true, "weight": 7, "urlFragment": "appendix-inventory-files-vars", "anchor": null, "singlePageAnchor": "appendix-inventory-files-vars", "sections": [{"title": "B.1. Ansible variables", "visible": true, "weight": 1, "urlFragment": "appendix-inventory-files-vars", "anchor": "ansible-variables", "singlePageAnchor": "ansible-variables"}, {"title": "B.2. Automation hub variables", "visible": true, "weight": 2, "urlFragment": "appendix-inventory-files-vars", "anchor": "hub-variables", "singlePageAnchor": "hub-variables"}, {"title": "B.3. Automation controller variables", "visible": true, "weight": 3, "urlFragment": "appendix-inventory-files-vars", "anchor": "controller-variables", "singlePageAnchor": "controller-variables"}, {"title": "B.4. Database variables", "visible": true, "weight": 4, "urlFragment": "appendix-inventory-files-vars", "anchor": "database-variables", "singlePageAnchor": "database-variables"}, {"title": "B.5. Event-Driven Ansible controller variables", "visible": true, "weight": 5, "urlFragment": "appendix-inventory-files-vars", "anchor": "event-driven-ansible-variables", "singlePageAnchor": "event-driven-ansible-variables"}, {"title": "B.6. General variables", "visible": true, "weight": 6, "urlFragment": "appendix-inventory-files-vars", "anchor": "general-variables", "singlePageAnchor": "general-variables"}, {"title": "B.7. Image variables", "visible": true, "weight": 7, "urlFragment": "appendix-inventory-files-vars", "anchor": "image-variables", "singlePageAnchor": "image-variables"}, {"title": "B.8. Platform gateway variables", "visible": true, "weight": 8, "urlFragment": "appendix-inventory-files-vars", "anchor": "platform-gateway-variables", "singlePageAnchor": "platform-gateway-variables"}, {"title": "B.9. Receptor variables", "visible": true, "weight": 9, "urlFragment": "appendix-inventory-files-vars", "anchor": "receptor-variables", "singlePageAnchor": "receptor-variables"}, {"title": "B.10. Redis variables", "visible": true, "weight": 10, "urlFragment": "appendix-inventory-files-vars", "anchor": "redis-variables", "singlePageAnchor": "redis-variables"}]}, {"title": "Legal Notice", "visible": true, "weight": 8, "urlFragment": "legal-notice", "anchor": null, "singlePageAnchor": "idm140359478264752"}]}