{"version": "1.1", "sections": [{"title": "RPM installation", "visible": true, "weight": 1, "urlFragment": "index", "anchor": null, "singlePageAnchor": null}, {"title": "Preface", "visible": true, "weight": 2, "urlFragment": "pr01", "anchor": null, "singlePageAnchor": "idm140368656778208"}, {"title": "Providing feedback on Red Hat documentation", "visible": true, "weight": 3, "urlFragment": "providing-feedback", "anchor": null, "singlePageAnchor": "providing-feedback"}, {"title": "1. Red Hat Ansible Automation Platform installation overview", "visible": true, "weight": 4, "urlFragment": "assembly-platform-install-overview", "anchor": null, "singlePageAnchor": "assembly-platform-install-overview", "sections": [{"title": "1.1. Prerequisites", "visible": true, "weight": 1, "urlFragment": "assembly-platform-install-overview", "anchor": "aap-installation-prereqs", "singlePageAnchor": "aap-installation-prereqs"}, {"title": "1.2. Managing Ansible Automation Platform subscriptions, updates, and support", "visible": true, "weight": 2, "urlFragment": "assembly-platform-install-overview", "anchor": "assembly-gateway-licensing", "singlePageAnchor": "assembly-gateway-licensing", "sections": [{"title": "1.2.1. Trial and evaluation", "visible": true, "weight": 1, "urlFragment": "assembly-platform-install-overview", "anchor": "ref-controller-trial-evaluation", "singlePageAnchor": "ref-controller-trial-evaluation"}, {"title": "1.2.2. Node counting in subscriptions", "visible": true, "weight": 2, "urlFragment": "assembly-platform-install-overview", "anchor": "ref-controller-node-counting", "singlePageAnchor": "ref-controller-node-counting"}, {"title": "1.2.3. Subscription Types", "visible": true, "weight": 3, "urlFragment": "assembly-platform-install-overview", "anchor": "ref-controller-subscription-types", "singlePageAnchor": "ref-controller-subscription-types"}, {"title": "1.2.4. Attaching your Red Hat Ansible Automation Platform subscription", "visible": true, "weight": 4, "urlFragment": "assembly-platform-install-overview", "anchor": "proc-attaching-subscriptions", "singlePageAnchor": "proc-attaching-subscriptions"}, {"title": "1.2.5. Obtaining a manifest file", "visible": true, "weight": 5, "urlFragment": "assembly-platform-install-overview", "anchor": "assembly-aap-obtain-manifest-files", "singlePageAnchor": "assembly-aap-obtain-manifest-files", "sections": [{"title": "1.2.5.1. Create a subscription allocation", "visible": false, "weight": 1, "urlFragment": "assembly-platform-install-overview", "anchor": "proc-create-subscription-allocation_obtain-manifest", "singlePageAnchor": "proc-create-subscription-allocation_obtain-manifest"}, {"title": "1.2.5.2. Adding subscriptions to a subscription allocation", "visible": false, "weight": 2, "urlFragment": "assembly-platform-install-overview", "anchor": "proc-add-merge-subscriptions", "singlePageAnchor": "proc-add-merge-subscriptions"}, {"title": "1.2.5.3. Downloading a manifest file", "visible": false, "weight": 3, "urlFragment": "assembly-platform-install-overview", "anchor": "proc-aap-generate-manifest-file", "singlePageAnchor": "proc-aap-generate-manifest-file"}]}, {"title": "1.2.6. Activating Red Hat Ansible Automation Platform", "visible": true, "weight": 6, "urlFragment": "assembly-platform-install-overview", "anchor": "assembly-aap-activate", "singlePageAnchor": "assembly-aap-activate", "sections": [{"title": "1.2.6.1. Activate with credentials", "visible": false, "weight": 1, "urlFragment": "assembly-platform-install-overview", "anchor": "proc-aap-activate-with-credentials", "singlePageAnchor": "proc-aap-activate-with-credentials"}, {"title": "1.2.6.2. Activate with a manifest file", "visible": false, "weight": 2, "urlFragment": "assembly-platform-install-overview", "anchor": "proc-aap-activate-with-manifest", "singlePageAnchor": "proc-aap-activate-with-manifest"}]}]}]}, {"title": "2. System requirements", "visible": true, "weight": 5, "urlFragment": "platform-system-requirements", "anchor": null, "singlePageAnchor": "platform-system-requirements", "sections": [{"title": "2.1. Prerequisites", "visible": true, "weight": 1, "urlFragment": "platform-system-requirements", "anchor": "prerequisites", "singlePageAnchor": "prerequisites"}, {"title": "2.2. Red Hat Ansible Automation Platform system requirements", "visible": true, "weight": 2, "urlFragment": "platform-system-requirements", "anchor": "ref-platform-system-requirements_licensing-gw", "singlePageAnchor": "ref-platform-system-requirements_licensing-gw", "sections": [{"title": "2.2.1. Repository requirements", "visible": true, "weight": 1, "urlFragment": "platform-system-requirements", "anchor": "repository_requirements", "singlePageAnchor": "repository_requirements"}, {"title": "2.2.2. Additional notes for Red Hat Ansible Automation Platform requirements", "visible": true, "weight": 2, "urlFragment": "platform-system-requirements", "anchor": "additional_notes_for_red_hat_ansible_automation_platform_requirements", "singlePageAnchor": "additional_notes_for_red_hat_ansible_automation_platform_requirements"}]}, {"title": "2.3. Platform gateway system requirements", "visible": true, "weight": 3, "urlFragment": "platform-system-requirements", "anchor": "ref-gateway-system-requirements", "singlePageAnchor": "ref-gateway-system-requirements"}, {"title": "2.4. Automation controller system requirements", "visible": true, "weight": 4, "urlFragment": "platform-system-requirements", "anchor": "ref-controller-system-requirements", "singlePageAnchor": "ref-controller-system-requirements"}, {"title": "2.5. Automation hub system requirements", "visible": true, "weight": 5, "urlFragment": "platform-system-requirements", "anchor": "ref-automation-hub-requirements", "singlePageAnchor": "ref-automation-hub-requirements", "sections": [{"title": "2.5.1. High availability automation hub requirements", "visible": true, "weight": 1, "urlFragment": "platform-system-requirements", "anchor": "ref-ha-hub-reqs", "singlePageAnchor": "ref-ha-hub-reqs", "sections": [{"title": "2.5.1.1. Required shared storage", "visible": false, "weight": 1, "urlFragment": "platform-system-requirements", "anchor": "required_shared_storage", "singlePageAnchor": "required_shared_storage"}, {"title": "2.5.1.2. Installing firewalld for HA hub deployment", "visible": false, "weight": 2, "urlFragment": "platform-system-requirements", "anchor": "installing_firewalld_for_ha_hub_deployment", "singlePageAnchor": "installing_firewalld_for_ha_hub_deployment"}]}]}, {"title": "2.6. Event-Driven Ansible controller system requirements", "visible": true, "weight": 6, "urlFragment": "platform-system-requirements", "anchor": "event-driven-ansible-system-requirements", "singlePageAnchor": "event-driven-ansible-system-requirements"}, {"title": "2.7. PostgreSQL requirements", "visible": true, "weight": 7, "urlFragment": "platform-system-requirements", "anchor": "ref-postgresql-requirements", "singlePageAnchor": "ref-postgresql-requirements", "sections": [{"title": "2.7.1. PostgreSQL Configurations", "visible": true, "weight": 1, "urlFragment": "platform-system-requirements", "anchor": "postgresql_configurations", "singlePageAnchor": "postgresql_configurations"}, {"title": "2.7.2. Setting up an external database", "visible": true, "weight": 2, "urlFragment": "platform-system-requirements", "anchor": "proc-setup-postgresql-ext-database_licensing-gw", "singlePageAnchor": "proc-setup-postgresql-ext-database_licensing-gw"}, {"title": "2.7.3. Enabling mutual TLS (mTLS) authentication", "visible": true, "weight": 3, "urlFragment": "platform-system-requirements", "anchor": "proc-enable-mtls-authentication_licensing-gw", "singlePageAnchor": "proc-enable-mtls-authentication_licensing-gw"}, {"title": "2.7.4. Using custom TLS certificates", "visible": true, "weight": 4, "urlFragment": "platform-system-requirements", "anchor": "proc-use-custom-tls-certificates_licensing-gw", "singlePageAnchor": "proc-use-custom-tls-certificates_licensing-gw"}, {"title": "2.7.5. Receptor certificate considerations", "visible": true, "weight": 5, "urlFragment": "platform-system-requirements", "anchor": "receptor-certificate-considerations", "singlePageAnchor": "receptor-certificate-considerations"}, {"title": "2.7.6. Enabling the hstore extension for the automation hub PostgreSQL database", "visible": true, "weight": 6, "urlFragment": "platform-system-requirements", "anchor": "proc-enable-hstore-extension", "singlePageAnchor": "proc-enable-hstore-extension"}, {"title": "2.7.7. Benchmarking storage performance for the Ansible Automation Platform PostgreSQL database", "visible": true, "weight": 7, "urlFragment": "platform-system-requirements", "anchor": "benchmark-postgresql", "singlePageAnchor": "benchmark-postgresql"}]}]}, {"title": "3. Backup and restore Ansible Automation Platform", "visible": true, "weight": 6, "urlFragment": "controller-backup-and-restore", "anchor": null, "singlePageAnchor": "controller-backup-and-restore", "sections": [{"title": "3.1. Backup and restoration considerations", "visible": true, "weight": 1, "urlFragment": "controller-backup-and-restore", "anchor": "controller-backup-restore-considerations", "singlePageAnchor": "controller-backup-restore-considerations"}, {"title": "3.2. Back up the Ansible Automation Platform", "visible": true, "weight": 2, "urlFragment": "controller-backup-and-restore", "anchor": "controller-backup-aap", "singlePageAnchor": "controller-backup-aap", "sections": [{"title": "3.2.1. Backup playbook", "visible": true, "weight": 1, "urlFragment": "controller-backup-and-restore", "anchor": "controller-backup-playbook", "singlePageAnchor": "controller-backup-playbook"}, {"title": "3.2.2. Back up the platform using automation installer", "visible": true, "weight": 2, "urlFragment": "controller-backup-and-restore", "anchor": "backup-using-automation-installer", "singlePageAnchor": "backup-using-automation-installer"}]}, {"title": "3.3. Restore Ansible Automation Platform", "visible": true, "weight": 3, "urlFragment": "controller-backup-and-restore", "anchor": "controller-restore-aap", "singlePageAnchor": "controller-restore-aap", "sections": [{"title": "3.3.1. Restore playbook", "visible": true, "weight": 1, "urlFragment": "controller-backup-and-restore", "anchor": "controller-restore-playbook", "singlePageAnchor": "controller-restore-playbook"}, {"title": "3.3.2. Restore the platform to its original state", "visible": true, "weight": 2, "urlFragment": "controller-backup-and-restore", "anchor": "proc-restore-aap", "singlePageAnchor": "proc-restore-aap"}]}]}, {"title": "4. Installing Red Hat Ansible Automation Platform", "visible": true, "weight": 7, "urlFragment": "assembly-platform-install-scenario", "anchor": null, "singlePageAnchor": "assembly-platform-install-scenario", "sections": [{"title": "4.1. Additional resources", "visible": true, "weight": 1, "urlFragment": "assembly-platform-install-scenario", "anchor": "additional_resources", "singlePageAnchor": "additional_resources"}, {"title": "4.2. Editing the Red Hat Ansible Automation Platform installer inventory file", "visible": true, "weight": 2, "urlFragment": "assembly-platform-install-scenario", "anchor": "ref-editing-installer-inventory-file_platform-install-scenario", "singlePageAnchor": "ref-editing-installer-inventory-file_platform-install-scenario", "sections": [{"title": "4.2.1. For an RPM installation", "visible": true, "weight": 1, "urlFragment": "assembly-platform-install-scenario", "anchor": "for_an_rpm_installation", "singlePageAnchor": "for_an_rpm_installation"}]}, {"title": "4.3. Inventory file examples based on installation scenarios", "visible": true, "weight": 3, "urlFragment": "assembly-platform-install-scenario", "anchor": "con-install-scenario-examples", "singlePageAnchor": "con-install-scenario-examples", "sections": [{"title": "4.3.1. Inventory file recommendations based on installation scenarios", "visible": true, "weight": 1, "urlFragment": "assembly-platform-install-scenario", "anchor": "con-install-scenario-recommendations", "singlePageAnchor": "con-install-scenario-recommendations", "sections": [{"title": "4.3.1.1. Single platform gateway and automation controller with an external (installer managed) database", "visible": false, "weight": 1, "urlFragment": "assembly-platform-install-scenario", "anchor": "ref-gateway-controller-ext-db", "singlePageAnchor": "ref-gateway-controller-ext-db"}, {"title": "4.3.1.2. Single platform gateway, automation controller, and automation hub with an external (installer managed) database", "visible": false, "weight": 2, "urlFragment": "assembly-platform-install-scenario", "anchor": "ref-gateway-controller-hub-ext-db", "singlePageAnchor": "ref-gateway-controller-hub-ext-db"}, {"title": "4.3.1.3. Single platform gateway, automation controller, automation hub, and Event-Driven Ansible controller with an external (installer managed) database", "visible": false, "weight": 3, "urlFragment": "assembly-platform-install-scenario", "anchor": "ref-gateway-controller-hub-eda-ext-db", "singlePageAnchor": "ref-gateway-controller-hub-eda-ext-db"}, {"title": "4.3.1.4. Installing high availability automation hub", "visible": false, "weight": 4, "urlFragment": "assembly-platform-install-scenario", "anchor": "ha-hub-installation", "singlePageAnchor": "ha-hub-installation"}, {"title": "4.3.1.5. Enabling a high availability (HA) deployment of automation hub on SELinux", "visible": false, "weight": 5, "urlFragment": "assembly-platform-install-scenario", "anchor": "proc-install-ha-hub-selinux", "singlePageAnchor": "proc-install-ha-hub-selinux", "sections": [{"title": "4.3.1.5.1. Configuring pulpcore.service", "visible": false, "weight": 1, "urlFragment": "assembly-platform-install-scenario", "anchor": "proc-configure-pulpcore-service", "singlePageAnchor": "proc-configure-pulpcore-service"}, {"title": "4.3.1.5.2. Applying the SELinux context", "visible": false, "weight": 2, "urlFragment": "assembly-platform-install-scenario", "anchor": "proc-apply-selinux-context", "singlePageAnchor": "proc-apply-selinux-context"}]}, {"title": "4.3.1.6. Configuring content signing on private automation hub", "visible": false, "weight": 6, "urlFragment": "assembly-platform-install-scenario", "anchor": "proc-configure-content-signing-on-pah", "singlePageAnchor": "proc-configure-content-signing-on-pah"}, {"title": "4.3.1.7. Adding a safe plugin variable to Event-Driven Ansible controller", "visible": false, "weight": 7, "urlFragment": "assembly-platform-install-scenario", "anchor": "proc-add-eda-safe-plugin-var", "singlePageAnchor": "proc-add-eda-safe-plugin-var"}]}, {"title": "4.3.2. Setting registry_username and registry_password", "visible": true, "weight": 2, "urlFragment": "assembly-platform-install-scenario", "anchor": "proc-set-registry-username-password", "singlePageAnchor": "proc-set-registry-username-password", "sections": [{"title": "4.3.2.1. Configuring Redis", "visible": false, "weight": 1, "urlFragment": "assembly-platform-install-scenario", "anchor": "redis-config-enterprise-topology_platform-install-scenario", "singlePageAnchor": "redis-config-enterprise-topology_platform-install-scenario"}]}]}, {"title": "4.4. Running the Red Hat Ansible Automation Platform installer setup script", "visible": true, "weight": 4, "urlFragment": "assembly-platform-install-scenario", "anchor": "proc-running-setup-script_platform-install-scenario", "singlePageAnchor": "proc-running-setup-script_platform-install-scenario"}, {"title": "4.5. Verifying installation of Ansible Automation Platform", "visible": true, "weight": 5, "urlFragment": "assembly-platform-install-scenario", "anchor": "proc-verify-aap-installation_platform-install-scenario", "singlePageAnchor": "proc-verify-aap-installation_platform-install-scenario"}, {"title": "4.6. Adding a subscription manifest to Ansible Automation Platform", "visible": true, "weight": 6, "urlFragment": "assembly-platform-install-scenario", "anchor": "con-adding-subscription-manifest", "singlePageAnchor": "con-adding-subscription-manifest"}]}, {"title": "5. Horizontal scaling in Red Hat Ansible Automation Platform", "visible": true, "weight": 8, "urlFragment": "assembly-horizontal-scaling", "anchor": null, "singlePageAnchor": "assembly-horizontal-scaling", "sections": [{"title": "5.1. Horizontal scaling in Event-Driven Ansible controller", "visible": true, "weight": 1, "urlFragment": "assembly-horizontal-scaling", "anchor": "con-hs-eda-controller", "singlePageAnchor": "con-hs-eda-controller", "sections": [{"title": "5.1.1. Sizing and scaling guidelines", "visible": true, "weight": 1, "urlFragment": "assembly-horizontal-scaling", "anchor": "con-hs-eda-sizing-scaling", "singlePageAnchor": "con-hs-eda-sizing-scaling"}, {"title": "5.1.2. Setting up horizontal scaling for Event-Driven Ansible controller", "visible": true, "weight": 2, "urlFragment": "assembly-horizontal-scaling", "anchor": "proc-hs-eda-setup", "singlePageAnchor": "proc-hs-eda-setup"}]}]}, {"title": "6. Disconnected installation", "visible": true, "weight": 9, "urlFragment": "disconnected-installation", "anchor": null, "singlePageAnchor": "disconnected-installation", "sections": [{"title": "6.1. Ansible Automation Platform installation on disconnected RHEL", "visible": true, "weight": 1, "urlFragment": "disconnected-installation", "anchor": "con-aap-installation-on-disconnected-rhel_disconnected-installation", "singlePageAnchor": "con-aap-installation-on-disconnected-rhel_disconnected-installation", "sections": [{"title": "6.1.1. System requirements for disconnected installation", "visible": true, "weight": 1, "urlFragment": "disconnected-installation", "anchor": "system_requirements_for_disconnected_installation", "singlePageAnchor": "system_requirements_for_disconnected_installation"}, {"title": "6.1.2. RPM Source", "visible": true, "weight": 2, "urlFragment": "disconnected-installation", "anchor": "rpm_source", "singlePageAnchor": "rpm_source"}]}, {"title": "6.2. Synchronizing RPM repositories using reposync", "visible": true, "weight": 2, "urlFragment": "disconnected-installation", "anchor": "proc-synchronizing-rpm-repositories-by-using-reposync_disconnected-installation", "singlePageAnchor": "proc-synchronizing-rpm-repositories-by-using-reposync_disconnected-installation"}, {"title": "6.3. Creating a new web server to host repositories", "visible": true, "weight": 3, "urlFragment": "disconnected-installation", "anchor": "proc-creating-a-new-web-server-to-host-repositories_disconnected-installation", "singlePageAnchor": "proc-creating-a-new-web-server-to-host-repositories_disconnected-installation"}, {"title": "6.4. Accessing RPM repositories from a locally mounted DVD", "visible": true, "weight": 4, "urlFragment": "disconnected-installation", "anchor": "accessing-rpm-repositories-for-locally-mounted-dvd_disconnected-installation", "singlePageAnchor": "accessing-rpm-repositories-for-locally-mounted-dvd_disconnected-installation"}, {"title": "6.5. Downloading and installing the Ansible Automation Platform setup bundle", "visible": true, "weight": 5, "urlFragment": "disconnected-installation", "anchor": "installing-the-aap-setup-bundle_disconnected-installation", "singlePageAnchor": "installing-the-aap-setup-bundle_disconnected-installation"}, {"title": "6.6. Completing post installation tasks", "visible": true, "weight": 6, "urlFragment": "disconnected-installation", "anchor": "completing-post-installation-tasks_disconnected-installation", "singlePageAnchor": "completing-post-installation-tasks_disconnected-installation"}]}, {"title": "7. Troubleshooting RPM installation of Ansible Automation Platform", "visible": true, "weight": 10, "urlFragment": "appendix-troubleshoot-rpm-aap", "anchor": null, "singlePageAnchor": "appendix-troubleshoot-rpm-aap", "sections": [{"title": "7.1. Gathering Ansible Automation Platform logs", "visible": true, "weight": 1, "urlFragment": "appendix-troubleshoot-rpm-aap", "anchor": "rpm-troubleshoot-generating-logs", "singlePageAnchor": "rpm-troubleshoot-generating-logs"}]}, {"title": "A. Inventory file variables", "visible": true, "weight": 11, "urlFragment": "appendix-inventory-files-vars", "anchor": null, "singlePageAnchor": "appendix-inventory-files-vars", "sections": [{"title": "A.1. Ansible variables", "visible": true, "weight": 1, "urlFragment": "appendix-inventory-files-vars", "anchor": "ansible-variables", "singlePageAnchor": "ansible-variables"}, {"title": "A.2. Automation hub variables", "visible": true, "weight": 2, "urlFragment": "appendix-inventory-files-vars", "anchor": "hub-variables", "singlePageAnchor": "hub-variables"}, {"title": "A.3. Automation controller variables", "visible": true, "weight": 3, "urlFragment": "appendix-inventory-files-vars", "anchor": "controller-variables", "singlePageAnchor": "controller-variables"}, {"title": "A.4. Database variables", "visible": true, "weight": 4, "urlFragment": "appendix-inventory-files-vars", "anchor": "database-variables", "singlePageAnchor": "database-variables"}, {"title": "A.5. Event-Driven Ansible controller variables", "visible": true, "weight": 5, "urlFragment": "appendix-inventory-files-vars", "anchor": "event-driven-ansible-variables", "singlePageAnchor": "event-driven-ansible-variables"}, {"title": "A.6. General variables", "visible": true, "weight": 6, "urlFragment": "appendix-inventory-files-vars", "anchor": "general-variables", "singlePageAnchor": "general-variables"}, {"title": "A.7. Image variables", "visible": true, "weight": 7, "urlFragment": "appendix-inventory-files-vars", "anchor": "image-variables", "singlePageAnchor": "image-variables"}, {"title": "A.8. Platform gateway variables", "visible": true, "weight": 8, "urlFragment": "appendix-inventory-files-vars", "anchor": "platform-gateway-variables", "singlePageAnchor": "platform-gateway-variables"}, {"title": "A.9. Receptor variables", "visible": true, "weight": 9, "urlFragment": "appendix-inventory-files-vars", "anchor": "receptor-variables", "singlePageAnchor": "receptor-variables"}, {"title": "A.10. Redis variables", "visible": true, "weight": 10, "urlFragment": "appendix-inventory-files-vars", "anchor": "redis-variables", "singlePageAnchor": "redis-variables"}, {"title": "A.11. Red Hat Ansible Lightspeed variables", "visible": true, "weight": 11, "urlFragment": "appendix-inventory-files-vars", "anchor": "lightspeed-variables", "singlePageAnchor": "lightspeed-variables", "sections": [{"title": "A.11.1. Red Hat Ansible Lightspeed variables", "visible": true, "weight": 1, "urlFragment": "appendix-inventory-files-vars", "anchor": "red_hat_ansible_lightspeed_variables", "singlePageAnchor": "red_hat_ansible_lightspeed_variables"}, {"title": "A.11.2. Ansible Lightspeed coding assistant variables", "visible": true, "weight": 2, "urlFragment": "appendix-inventory-files-vars", "anchor": "ansible_lightspeed_coding_assistant_variables", "singlePageAnchor": "ansible_lightspeed_coding_assistant_variables"}, {"title": "A.11.3. Ansible Lightspeed intelligent assistant variables", "visible": true, "weight": 3, "urlFragment": "appendix-inventory-files-vars", "anchor": "ansible_lightspeed_intelligent_assistant_variables", "singlePageAnchor": "ansible_lightspeed_intelligent_assistant_variables"}, {"title": "A.11.4. Ansible Lightspeed intelligent assistant integration with MCP server variables", "visible": true, "weight": 4, "urlFragment": "appendix-inventory-files-vars", "anchor": "ansible_lightspeed_intelligent_assistant_integration_with_mcp_server_variables", "singlePageAnchor": "ansible_lightspeed_intelligent_assistant_integration_with_mcp_server_variables"}]}, {"title": "A.12. Ansible MCP server variables", "visible": true, "weight": 12, "urlFragment": "appendix-inventory-files-vars", "anchor": "ansible-mcp-server-variables", "singlePageAnchor": "ansible-mcp-server-variables"}]}, {"title": "Legal Notice", "visible": true, "weight": 12, "urlFragment": "legal-notice", "anchor": null, "singlePageAnchor": "idm140368664940656"}]}