{
  "version": "1.1",
  "sections": [
    {
      "title": "Claims for workload identity",
      "visible": true,
      "weight": 1,
      "urlFragment": "index",
      "anchor": null,
      "singlePageAnchor": null,
      "sections": [
        {
          "title": "Example claims",
          "visible": true,
          "weight": 1,
          "urlFragment": "GUID-274163f4-8d73-4459-9919-56d73908cdbb__section_1",
          "anchor": null,
          "singlePageAnchor": "GUID-274163f4-8d73-4459-9919-56d73908cdbb__section_1"
        },
        {
          "title": "Standard Claims",
          "visible": true,
          "weight": 2,
          "urlFragment": "GUID-274163f4-8d73-4459-9919-56d73908cdbb__section_2",
          "anchor": null,
          "singlePageAnchor": "GUID-274163f4-8d73-4459-9919-56d73908cdbb__section_2"
        },
        {
          "title": "Custom claims",
          "visible": true,
          "weight": 3,
          "urlFragment": "GUID-274163f4-8d73-4459-9919-56d73908cdbb__section_3",
          "anchor": null,
          "singlePageAnchor": "GUID-274163f4-8d73-4459-9919-56d73908cdbb__section_3"
        }
      ]
    }
  ]
}