{
  "version": "1.1",
  "sections": [
    {
      "title": "Custom UI components and filters",
      "visible": true,
      "weight": 1,
      "urlFragment": "index",
      "anchor": null,
      "singlePageAnchor": null,
      "sections": [
        {
          "title": "AAPTokenField",
          "visible": true,
          "weight": 1,
          "urlFragment": "devtools-aap-token-field",
          "anchor": null,
          "singlePageAnchor": "devtools-aap-token-field"
        },
        {
          "title": "AAPResourcePicker",
          "visible": true,
          "weight": 2,
          "urlFragment": "devtools-aap-resource-picker",
          "anchor": null,
          "singlePageAnchor": "devtools-aap-resource-picker"
        },
        {
          "title": "Custom filters",
          "visible": true,
          "weight": 3,
          "urlFragment": "devtools-custom-filters",
          "anchor": null,
          "singlePageAnchor": "devtools-custom-filters"
        }
      ]
    }
  ]
}